pydataweaver/__init__.py
pydataweaver/__main__.py
pydataweaver/_version.py
pydataweaver/compile.py
pydataweaver/lscolumns.py
pydataweaver/term_size.py
pydataweaver/engines/__init__.py
pydataweaver/engines/postgres.py
pydataweaver/engines/sqlite.py
pydataweaver/lib/__init__.py
pydataweaver/lib/cleanup.py
pydataweaver/lib/compile.py
pydataweaver/lib/datapackage.py
pydataweaver/lib/datasets.py
pydataweaver/lib/defaults.py
pydataweaver/lib/download.py
pydataweaver/lib/dummy.py
pydataweaver/lib/engine.py
pydataweaver/lib/engine_tools.py
pydataweaver/lib/get_opts.py
pydataweaver/lib/install.py
pydataweaver/lib/load_json.py
pydataweaver/lib/models.py
pydataweaver/lib/process.py
pydataweaver/lib/repository.py
pydataweaver/lib/scripts.py
pydataweaver/lib/table.py
pydataweaver/lib/templates.py
pydataweaver/lib/tools.py
pydataweaver/lib/warning.py
pydataweaver-1.0.0.data/data/CITATION
pydataweaver-1.0.0.dist-info/LICENSE
pydataweaver-1.0.0.dist-info/METADATA
pydataweaver-1.0.0.dist-info/WHEEL
pydataweaver-1.0.0.dist-info/entry_points.txt
pydataweaver-1.0.0.dist-info/top_level.txt
pydataweaver-1.0.0.dist-info/RECORD
