Metadata-Version: 2.1
Name: pydataweaver
Version: 1.0.0
Summary: Pydata Weaver
Home-page: https://github.com/weecology/pydataweaver
Author: Henry Senyondo, Andrew Zhang, Ethan White
Author-email: ethan@weecology.org
License: UNKNOWN
Platform: UNKNOWN
Classifier: Intended Audience :: Science/Research
Classifier: License :: OSI Approved :: MIT License
Classifier: Operating System :: Microsoft :: Windows
Classifier: Operating System :: POSIX
Classifier: Operating System :: Unix
Classifier: Programming Language :: Python
Classifier: Programming Language :: Python :: 3.5
Classifier: Programming Language :: Python :: 3.6
Classifier: Programming Language :: Python :: 3.7
Classifier: Programming Language :: Python :: Implementation :: PyPy
Classifier: Topic :: Software Development :: Libraries :: Python Modules
Classifier: Topic :: Scientific/Engineering :: GIS
Classifier: Topic :: Scientific/Engineering :: Information Analysis
Classifier: Topic :: Database
Requires-Dist: xlrd
Requires-Dist: future
Requires-Dist: argcomplete
